alibabacloud_dingtalk/__init__.py
alibabacloud_dingtalk/activity_1_0/__init__.py
alibabacloud_dingtalk/activity_1_0/client.py
alibabacloud_dingtalk/activity_1_0/models.py
alibabacloud_dingtalk/agoal_1_0/__init__.py
alibabacloud_dingtalk/agoal_1_0/client.py
alibabacloud_dingtalk/agoal_1_0/models.py
alibabacloud_dingtalk/ai_global_e_c_1_0/__init__.py
alibabacloud_dingtalk/ai_global_e_c_1_0/client.py
alibabacloud_dingtalk/ai_global_e_c_1_0/models.py
alibabacloud_dingtalk/ai_interaction_1_0/__init__.py
alibabacloud_dingtalk/ai_interaction_1_0/client.py
alibabacloud_dingtalk/ai_interaction_1_0/models.py
alibabacloud_dingtalk/ai_paa_s_1_0/__init__.py
alibabacloud_dingtalk/ai_paa_s_1_0/client.py
alibabacloud_dingtalk/ai_paa_s_1_0/models.py
alibabacloud_dingtalk/algo_1_0/__init__.py
alibabacloud_dingtalk/algo_1_0/client.py
alibabacloud_dingtalk/algo_1_0/models.py
alibabacloud_dingtalk/alitrip_1_0/__init__.py
alibabacloud_dingtalk/alitrip_1_0/client.py
alibabacloud_dingtalk/alitrip_1_0/models.py
alibabacloud_dingtalk/amdp_1_0/__init__.py
alibabacloud_dingtalk/amdp_1_0/client.py
alibabacloud_dingtalk/amdp_1_0/models.py
alibabacloud_dingtalk/apaas_1_0/__init__.py
alibabacloud_dingtalk/apaas_1_0/client.py
alibabacloud_dingtalk/apaas_1_0/models.py
alibabacloud_dingtalk/app_market_1_0/__init__.py
alibabacloud_dingtalk/app_market_1_0/client.py
alibabacloud_dingtalk/app_market_1_0/models.py
alibabacloud_dingtalk/assistant_1_0/__init__.py
alibabacloud_dingtalk/assistant_1_0/client.py
alibabacloud_dingtalk/assistant_1_0/models.py
alibabacloud_dingtalk/assistant_2_0/__init__.py
alibabacloud_dingtalk/assistant_2_0/client.py
alibabacloud_dingtalk/assistant_2_0/models.py
alibabacloud_dingtalk/ats_1_0/__init__.py
alibabacloud_dingtalk/ats_1_0/client.py
alibabacloud_dingtalk/ats_1_0/models.py
alibabacloud_dingtalk/attendance_1_0/__init__.py
alibabacloud_dingtalk/attendance_1_0/client.py
alibabacloud_dingtalk/attendance_1_0/models.py
alibabacloud_dingtalk/badge_1_0/__init__.py
alibabacloud_dingtalk-2.2.38.dist-info/LICENSE
alibabacloud_dingtalk-2.2.38.dist-info/METADATA
alibabacloud_dingtalk-2.2.38.dist-info/WHEEL
alibabacloud_dingtalk-2.2.38.dist-info/top_level.txt
alibabacloud_dingtalk-2.2.38.dist-info/RECORD
